LICENSE
MANIFEST.in
README.md
setup.cfg
setup.py
flaskcode/__init__.py
flaskcode/__main__.py
flaskcode/__pkginfo__.py
flaskcode/cli.py
flaskcode/default_config.py
flaskcode/utils.py
flaskcode/views.py
flaskcode.egg-info/PKG-INFO
flaskcode.egg-info/SOURCES.txt
flaskcode.egg-info/dependency_links.txt
flaskcode.egg-info/entry_points.txt
flaskcode.egg-info/not-zip-safe
flaskcode.egg-info/requires.txt
flaskcode.egg-info/top_level.txt
flaskcode/static/css/styles.css
flaskcode/static/img/favicon.ico
flaskcode/static/img/logo.png
flaskcode/static/js/flaskcode.js
flaskcode/static/js/objects.js
flaskcode/static/vendor/jquery.min.js
flaskcode/static/vendor/bootstrap/css/bootstrap-theme.css
flaskcode/static/vendor/bootstrap/css/bootstrap-theme.css.map
flaskcode/static/vendor/bootstrap/css/bootstrap-theme.min.css
flaskcode/static/vendor/bootstrap/css/bootstrap-theme.min.css.map
flaskcode/static/vendor/bootstrap/css/bootstrap.css
flaskcode/static/vendor/bootstrap/css/bootstrap.css.map
flaskcode/static/vendor/bootstrap/css/bootstrap.min.css
flaskcode/static/vendor/bootstrap/css/bootstrap.min.css.map
flaskcode/static/vendor/bootstrap/fonts/glyphicons-halflings-regular.eot
flaskcode/static/vendor/bootstrap/fonts/glyphicons-halflings-regular.svg
flaskcode/static/vendor/bootstrap/fonts/glyphicons-halflings-regular.ttf
flaskcode/static/vendor/bootstrap/fonts/glyphicons-halflings-regular.woff
flaskcode/static/vendor/bootstrap/fonts/glyphicons-halflings-regular.woff2
flaskcode/static/vendor/bootstrap/js/bootstrap.js
flaskcode/static/vendor/bootstrap/js/bootstrap.min.js
flaskcode/static/vendor/bootstrap/js/npm.js
flaskcode/static/vendor/font-awesome/css/font-awesome.css
flaskcode/static/vendor/font-awesome/css/font-awesome.min.css
flaskcode/static/vendor/font-awesome/fonts/FontAwesome.otf
flaskcode/static/vendor/font-awesome/fonts/fontawesome-webfont.eot
flaskcode/static/vendor/font-awesome/fonts/fontawesome-webfont.svg
flaskcode/static/vendor/font-awesome/fonts/fontawesome-webfont.ttf
flaskcode/static/vendor/font-awesome/fonts/fontawesome-webfont.woff
flaskcode/static/vendor/font-awesome/fonts/fontawesome-webfont.woff2
flaskcode/static/vendor/jquery-contextMenu/jquery.contextMenu.css
