Metadata-Version: 2.1
Name: flaskcode
Version: 0.0.8
Summary: Web based code editor on python flask framework
Home-page: https://github.com/sujeetkv/flaskcode
Author: Sujeet Kumar
Author-email: sujeetkv90@gmail.com
License: MIT
Keywords: flaskcode code editor code-editor
Platform: any
Classifier: Development Status :: 3 - Alpha
Classifier: Intended Audience :: Developers
Classifier: Programming Language :: Python
Classifier: Programming Language :: Python :: 3.6
Classifier: License :: OSI Approved :: MIT License
Classifier: Operating System :: OS Independent
Classifier: Topic :: Internet :: WWW/HTTP
Classifier: Topic :: Text Editors :: Text Processing
Classifier: Topic :: Software Development :: Libraries :: Python Modules
Classifier: Topic :: Utilities
Requires-Python: >=3.6
